setup.py
TwiLiX.egg-info/PKG-INFO
TwiLiX.egg-info/SOURCES.txt
TwiLiX.egg-info/dependency_links.txt
TwiLiX.egg-info/requires.txt
TwiLiX.egg-info/top_level.txt
twilix/__init__.py
twilix/delay.py
twilix/disco.py
twilix/dispatcher.py
twilix/errors.py
twilix/fields.py
twilix/htmlim.py
twilix/jid.py
twilix/register.py
twilix/si.py
twilix/stanzas.py
twilix/utils.py
twilix/vcard.py
twilix/version.py
twilix/base/__init__.py
twilix/base/exceptions.py
twilix/base/myelement.py
twilix/base/velement.py
twilix/bytestreams/__init__.py
twilix/bytestreams/ibb/__init__.py
twilix/bytestreams/ibb/base.py
twilix/bytestreams/ibb/stanzas.py
twilix/bytestreams/socks5/__init__.py
twilix/bytestreams/socks5/base.py
twilix/bytestreams/socks5/proxy65.py
twilix/bytestreams/socks5/socks5.py
twilix/bytestreams/socks5/stanzas.py
twilix/ft/__init__.py
twilix/ft/si.py
twilix/muc/__init__.py
twilix/muc/admin.py
twilix/muc/connect.py
twilix/muc/user.py
twilix/patterns/__init__.py
twilix/patterns/client.py
twilix/patterns/component.py
twilix/pubsub/__init__.py
twilix/pubsub/base.py
twilix/pubsub/payloads/__init__.py
twilix/pubsub/payloads/geoloc.py
twilix/roster/__init__.py
twilix/test/__init__.py
twilix/test/test_disco.py
twilix/test/test_dispatcher.py
twilix/test/test_errors.py
twilix/test/test_fields.py
twilix/test/test_jid.py
twilix/test/test_myelement.py
twilix/test/test_roster.py
twilix/test/test_stanzas.py
twilix/test/test_utils.py
twilix/test/test_vcard.py
twilix/test/test_velement.py
twilix/test/test_version.py