Metadata-Version: 1.0
Name: TwiLiX
Version: 0.1.3
Summary: ORM based XMPP library for Twisted
Home-page: https://github.com/jbinary/twilix
Author: Sergey Dobrov
Author-email: binary@jrudevels.org
License: LICENSE.txt
Platform: UNKNOWN
